LICENSE
MANIFEST.in
README.rst
pyproject.toml
setup.cfg
setup.py
django_bt5_modulo.egg-info/PKG-INFO
django_bt5_modulo.egg-info/SOURCES.txt
django_bt5_modulo.egg-info/dependency_links.txt
django_bt5_modulo.egg-info/requires.txt
django_bt5_modulo.egg-info/top_level.txt
modulo/__init__.py
modulo/admin.py
modulo/apps.py
modulo/forms.py
modulo/models.py
modulo/tests.py
modulo/urls.py
modulo/views.py
modulo/clases/__init__.py
modulo/clases/select2.py
modulo/clases/table_lista.py
modulo/migrations/0001_initial.py
modulo/migrations/0002_testdata_is_enable.py
modulo/migrations/__init__.py
modulo/static/modulo/js/lista.js
modulo/static/modulo/js/lista.min.js
modulo/static/modulo/js/modulo.js
modulo/static/modulo/js/modulo.min.js
modulo/static/modulo/js/table.js
modulo/static/modulo/js/table.min.js
modulo/static/modulo/plugins/bootstrap/bootstrap-icons/LICENSE.md
modulo/static/modulo/plugins/bootstrap/bootstrap-icons/README.md
modulo/static/modulo/plugins/bootstrap/bootstrap-icons/bootstrap-icons.svg
modulo/static/modulo/plugins/bootstrap/bootstrap-icons/package-lock.json
modulo/static/modulo/plugins/bootstrap/bootstrap-icons/package.json
modulo/static/modulo/plugins/bootstrap/bootstrap-icons/font/bootstrap-icons.css
modulo/static/modulo/plugins/bootstrap/bootstrap-icons/font/bootstrap-icons.json
modulo/static/modulo/plugins/bootstrap/bootstrap-icons/font/bootstrap-icons.scss
modulo/static/modulo/plugins/bootstrap/bootstrap-icons/font/index.html
modulo/static/modulo/plugins/bootstrap/bootstrap-icons/font/fonts/bootstrap-icons.woff
modulo/static/modulo/plugins/bootstrap/bootstrap-icons/font/fonts/bootstrap-icons.woff2
modulo/static/modulo/plugins/bootstrap/bootstrap-icons/icons/123.svg
modulo/static/modulo/plugins/bootstrap/bootstrap-icons/icons/activity.svg
modulo/static/modulo/plugins/bootstrap/bootstrap-icons/icons/alarm-fill.svg
modulo/static/modulo/plugins/bootstrap/bootstrap-icons/icons/alarm.svg
modulo/static/modulo/plugins/bootstrap/bootstrap-icons/icons/align-bottom.svg
modulo/static/modulo/plugins/bootstrap/bootstrap-icons/icons/align-center.svg
modulo/static/modulo/plugins/bootstrap/bootstrap-icons/icons/align-end.svg
