Metadata-Version: 2.1
Name: django-bt5-modulo
Version: 0.6.1
Summary: A Django app to conduct web-based bootstrap5, select2, CRUD, TABLE.
Home-page: https://pypi.org/project/django-bootstrap5-modulo/
Author: Carlos Y. Ruiz Vasquez
Author-email: xcarlx2@hotmail.com
License: MIT License  # Example license
Classifier: Environment :: Web Environment
Classifier: Framework :: Django
Classifier: Intended Audience :: Developers
Classifier: License :: OSI Approved :: BSD License
Classifier: Operating System :: OS Independent
Classifier: Programming Language :: Python
Classifier: Programming Language :: Python :: 3
Classifier: Programming Language :: Python :: 3 :: Only
Classifier: Programming Language :: Python :: 3.10
Classifier: Programming Language :: Python :: 3.11
Classifier: Programming Language :: Python :: 3.12
Classifier: Topic :: Internet :: WWW/HTTP
Classifier: Topic :: Internet :: WWW/HTTP :: Dynamic Content
Requires-Python: >=3.8
License-File: LICENSE
Requires-Dist: Django>=4.2
